ProPyCore/__init__.py
ProPyCore/exceptions.py
ProPyCore/procore.py
ProPyCore/access/__init__.py
ProPyCore/access/base.py
ProPyCore/access/change_events.py
ProPyCore/access/companies.py
ProPyCore/access/cost_codes.py
ProPyCore/access/direct_costs.py
ProPyCore/access/generic_tools.py
ProPyCore/access/permissions.py
ProPyCore/access/projects.py
ProPyCore/access/rfis.py
ProPyCore/access/submittals.py
ProPyCore/access/tasks.py
ProPyCore/access/budgets/__init__.py
ProPyCore/access/budgets/columns.py
ProPyCore/access/budgets/details.py
ProPyCore/access/budgets/rows.py
ProPyCore/access/budgets/views.py
ProPyCore/access/directory/__init__.py
ProPyCore/access/directory/people.py
ProPyCore/access/directory/roles.py
ProPyCore/access/directory/trades.py
ProPyCore/access/directory/users.py
ProPyCore/access/directory/vendors.py
ProPyCore/access/documents/__init__.py
ProPyCore/access/documents/files.py
ProPyCore/access/documents/folders.py
ProPyCore/access/photos/__init__.py
ProPyCore/access/photos/categories.py
ProPyCore/access/photos/images.py
ProPyCore/access/quality/__init__.py
ProPyCore/access/quality/punch.py
ProPyCore/access/time/__init__.py
ProPyCore/access/time/timecards.py
ProPyCore/access/time/timesheets.py
ProPyCore/utils/__init__.py
ProPyCore/utils/logger.py
propycore-0.7.0.dist-info/licenses/LICENSE
tests/unit/__init__.py
tests/unit/test_budgets_columns.py
tests/unit/test_budgets_details.py
tests/unit/test_budgets_rows.py
tests/unit/test_budgets_views.py
tests/unit/test_companies.py
tests/unit/test_cost_codes.py
tests/unit/test_direct_costs.py
tests/unit/test_files.py
tests/unit/test_folders.py
tests/unit/test_generic_tools.py
tests/unit/test_projects.py
tests/unit/test_rfis.py
tests/unit/test_submittals.py
tests/unit/test_tasks.py
tests/unit/test_timecards.py
propycore-0.7.0.dist-info/METADATA
propycore-0.7.0.dist-info/WHEEL
propycore-0.7.0.dist-info/top_level.txt
propycore-0.7.0.dist-info/RECORD
