Metadata-Version: 2.4
Name: ProPyCore
Version: 0.7.0
Summary: Interact with Procore through Python for data connection applications
Home-page: https://github.com/rogers-obrien-rad/ProPyCore
Author: Hagen E. Fritz
Author-email: hfritz@r-o.com
Keywords: procore,api,python,sdk
Classifier: Programming Language :: Python :: 3
Classifier: Intended Audience :: Developers
Classifier: License :: OSI Approved :: MIT License
Classifier: Operating System :: OS Independent
Requires-Python: >=3.6
License-File: LICENSE
Requires-Dist: beautifulsoup4
Requires-Dist: requests
Requires-Dist: fuzzywuzzy
Requires-Dist: python-Levenshtein
Dynamic: author
Dynamic: author-email
Dynamic: classifier
Dynamic: description
Dynamic: description-content-type
Dynamic: home-page
Dynamic: keywords
Dynamic: license-file
Dynamic: requires-dist
Dynamic: requires-python
Dynamic: summary
